accumulator/__init__.py
accumulator/accumulator.py
accumulator-0.3.dist-info/DESCRIPTION.rst
accumulator-0.3.dist-info/METADATA
accumulator-0.3.dist-info/RECORD
accumulator-0.3.dist-info/WHEEL
accumulator-0.3.dist-info/metadata.json
accumulator-0.3.dist-info/top_level.txt
