Metadata-Version: 2.0
Name: accumulator
Version: 0.3
Summary: A framework for the accumulation of occurrences with subjects.
Home-page: https://github.com/rochars/accumulator
Author: Rafael da Silva Rocha
Author-email: rocha.rafaelsilva@gmail.com
License: MIT
Keywords: accumulator state event occurrence subject log financial cost stock asset
Platform: UNKNOWN
Classifier: Development Status :: 3 - Alpha
Classifier: Intended Audience :: Developers
Classifier: Topic :: Software Development
Classifier: License :: OSI Approved :: MIT License
Classifier: Programming Language :: Python :: 2.7
Classifier: Programming Language :: Python :: 3.3
Classifier: Programming Language :: Python :: 3.4
Classifier: Programming Language :: Python :: 3.5
